incountry/__init__.py
incountry/__version__.py
incountry/countries_cache.py
incountry/crypto_utils.py
incountry/http_client.py
incountry/http_request.py
incountry/incountry_crypto.py
incountry/py.typed
incountry/retry.py
incountry/secret_key_accessor.py
incountry/storage.py
incountry/types.py
incountry/backport/__init__.py
incountry/backport/fromisoformat.py
incountry/exceptions/__init__.py
incountry/exceptions/storage_client_exception.py
incountry/exceptions/storage_crypto_exception.py
incountry/exceptions/storage_exception.py
incountry/exceptions/storage_server_exception.py
incountry/models/__init__.py
incountry/models/attachment_create.py
incountry/models/attachment_meta.py
incountry/models/attachment_meta_update.py
incountry/models/attachment_request.py
incountry/models/batch_delete_filter.py
incountry/models/countries_data.py
incountry/models/country.py
incountry/models/custom_encryption_config.py
incountry/models/custom_encryption_config_method_validation.py
incountry/models/custom_encryption_validation.py
incountry/models/find_filter.py
incountry/models/http_attachment_meta.py
incountry/models/http_options.py
incountry/models/http_record_batch_write.py
incountry/models/http_record_delete.py
incountry/models/http_record_find.py
incountry/models/http_record_read.py
incountry/models/http_record_write.py
incountry/models/record.py
incountry/models/record_from_server.py
incountry/models/record_list_for_batch.py
incountry/models/request_options.py
incountry/models/secret_key_accessor_model.py
incountry/models/secrets_data.py
incountry/models/secrets_validation.py
incountry/models/sort_filter.py
incountry/models/storage_with_env.py
incountry/models/common/__init__.py
incountry/models/common/custom_types.py
incountry/token_clients/__init__.py
incountry/token_clients/oauth_token_client.py
incountry/token_clients/static_token_client.py
incountry/token_clients/token_client.py
incountry/validation/__init__.py
incountry/validation/utils.py
incountry-5.0.0.dist-info/METADATA
incountry-5.0.0.dist-info/WHEEL
incountry-5.0.0.dist-info/top_level.txt
incountry-5.0.0.dist-info/RECORD
