Metadata-Version: 2.1
Name: incountry
Version: 5.0.0
Summary: InCountry Storage SDK
Home-page: https://github.com/incountry/sdk-python
Author: InCountry
Author-email: sdks@incountry.com
License: MIT
Platform: UNKNOWN
Classifier: License :: OSI Approved :: MIT License
Classifier: Programming Language :: Python
Classifier: Programming Language :: Python :: 3
Classifier: Programming Language :: Python :: 3.6
Classifier: Programming Language :: Python :: Implementation :: CPython
Classifier: Programming Language :: Python :: Implementation :: PyPy
Requires-Python: >=3.6.0
Requires-Dist: requests
Requires-Dist: cryptography
Requires-Dist: pydantic
